odoo/addons/payroll_hr_public_holidays/README.rst
odoo/addons/payroll_hr_public_holidays/__init__.py
odoo/addons/payroll_hr_public_holidays/__manifest__.py
odoo/addons/payroll_hr_public_holidays/i18n/es_AR.po
odoo/addons/payroll_hr_public_holidays/i18n/it.po
odoo/addons/payroll_hr_public_holidays/i18n/payroll_hr_public_holidays.pot
odoo/addons/payroll_hr_public_holidays/i18n/pt.po
odoo/addons/payroll_hr_public_holidays/i18n/pt_BR.po
odoo/addons/payroll_hr_public_holidays/models/__init__.py
odoo/addons/payroll_hr_public_holidays/models/hr_payslip.py
odoo/addons/payroll_hr_public_holidays/readme/CONTRIBUTORS.md
odoo/addons/payroll_hr_public_holidays/readme/DESCRIPTION.md
odoo/addons/payroll_hr_public_holidays/readme/USAGE.md
odoo/addons/payroll_hr_public_holidays/static/description/icon.png
odoo/addons/payroll_hr_public_holidays/static/description/index.html
odoo/addons/payroll_hr_public_holidays/tests/__init__.py
odoo/addons/payroll_hr_public_holidays/tests/test_hr_payslip.py
odoo_addon_payroll_hr_public_holidays-17.0.1.0.0.4.dist-info/METADATA
odoo_addon_payroll_hr_public_holidays-17.0.1.0.0.4.dist-info/WHEEL
odoo_addon_payroll_hr_public_holidays-17.0.1.0.0.4.dist-info/top_level.txt
odoo_addon_payroll_hr_public_holidays-17.0.1.0.0.4.dist-info/RECORD
