Metadata-Version: 2.1
Name: odoo-addon-payroll_hr_public_holidays
Version: 17.0.1.0.0.4
Requires-Python: >=3.10
Requires-Dist: odoo-addon-hr_holidays_public>=17.0dev,<17.1dev
Requires-Dist: odoo-addon-payroll>=17.0dev,<17.1dev
Requires-Dist: odoo>=17.0a,<17.1dev
Summary: Integration between payroll and hr_public_holidays
Home-page: https://github.com/OCA/payroll
License: AGPL-3
Author: Nimarosa, Odoo Community Association (OCA)
Author-email: support@odoo-community.org
Classifier: Programming Language :: Python
Classifier: Framework :: Odoo
Classifier: Framework :: Odoo :: 17.0
Classifier: License :: OSI Approved :: GNU Affero General Public License v3
